LICENSE
MANIFEST.in
README.md
setup.py
django_keoh_kstore.egg-info/PKG-INFO
django_keoh_kstore.egg-info/SOURCES.txt
django_keoh_kstore.egg-info/dependency_links.txt
django_keoh_kstore.egg-info/top_level.txt
docs/empty
kstore/__init__.py
kstore/admin/__init__.py
kstore/context_processors/__init__.py
kstore/forms/__init__.py
kstore/forms/mail.py
kstore/helpers/__init__.py
kstore/helpers/dates.py
kstore/helpers/mixins.py
kstore/management/__init__.py
kstore/management/commands/__init__.py
kstore/management/commands/basic_config.py
kstore/management/commands/recuento.py
kstore/managers/__init__.py
kstore/managers/mail.py
kstore/managers/products.py
kstore/migrations/0001_initial.py
kstore/migrations/0002_product.py
kstore/migrations/0003_mailmessage.py
kstore/migrations/0004_auto_20151218_1830.py
kstore/migrations/0005_mailmessage_readed.py
kstore/migrations/0006_mailmessage_message.py
kstore/migrations/0007_mailmessage_sended.py
kstore/migrations/0008_mailcontact.py
kstore/migrations/0009_mailcontact_owner.py
kstore/migrations/0010_mailmessage_sended_at.py
kstore/migrations/0011_mailmessage_slug.py
kstore/migrations/0012_basicconfiguration_theme.py
kstore/migrations/0013_auto_20160215_1028.py
kstore/migrations/0014_mailmessage_important.py
kstore/migrations/0015_auto_20160215_1223.py
kstore/migrations/0016_auto_20160215_1630.py
kstore/migrations/__init__.py
kstore/models/__init__.py
kstore/models/abstracts.py
kstore/models/config.py
kstore/models/mail.py
kstore/models/manufacturers.py
kstore/models/products.py
kstore/models/suppliers.py
kstore/templates/kstore/superbase.html
kstore/templates/kstore/dashboard/home.html
kstore/templates/kstore/mail/compose_mail.html
kstore/templates/kstore/mail/draft.html
kstore/templates/kstore/mail/important.html
kstore/templates/kstore/mail/inbox.html
kstore/templates/kstore/mail/mail_base.html
kstore/templates/kstore/mail/mailmessage_detail.html
kstore/templates/kstore/mail/sent.html
kstore/templates/kstore/parts/header.html
kstore/templates/kstore/parts/navbar.html
kstore/templates/kstore/products/index.html
kstore/tests/__init__.py
kstore/urls/__init__.py
kstore/urls/mail.py
