Metadata-Version: 1.1
Name: django-keoh-kstore
Version: 0.0.2
Summary: A simple Django app to create shops
Home-page: https://github.com/KeoH/django-keoh-kstore
Author: Francisco Manzano Magaña
Author-email: keoh77@gmail.com
License: BSD License
Platform: UNKNOWN
Classifier: Environment :: Web Environment
Classifier: Framework :: Django
Classifier: Intended Audience :: Developers
Classifier: License :: OSI Approved :: BSD License
Classifier: Operating System :: OS Independent
Classifier: Programming Language :: Python
Classifier: Programming Language :: Python :: 2.6
Classifier: Programming Language :: Python :: 2.7
Classifier: Topic :: Internet :: WWW/HTTP
Classifier: Topic :: Internet :: WWW/HTTP :: Dynamic Content
